fifo.v
module fifo (
    input clk,
    input rst_n,
    input wr_en,                   // Write enable
    input rd_en,                   // Read enable
    input [15:0] data_in,          // 16-bit input data
    output reg [15:0] data_out,    // 16-bit output data
    output reg full,               // FIFO full flag
    output reg empty               // FIFO empty flag
);
    parameter FIFO_DEPTH = 32;     // FIFO depth of 32 elements (each 8 bits wide)

    reg [7:0] fifo [0:FIFO_DEPTH-1]; // 32x8 FIFO memory to store 1 byte per element
    reg [4:0] wr_ptr, rd_ptr;         // 5-bit write and read pointers (0-31 range)
    reg [5:0] count;                  // Counter for elements in the FIFO (0-32 range)

    // Sequential logic for read and write operations
    always @(posedge clk or negedge rst_n) begin
        if (!rst_n) begin
            wr_ptr <= 0;
            rd_ptr <= 0;
            count <= 0;
            full <= 0;
            empty <= 1;
            data_out <= 16'b0; // Initialize output data
        end else begin
            // Write operation (16-bit data split into two 8-bit parts)
            if (wr_en && (count <= FIFO_DEPTH - 2)) begin
                fifo[wr_ptr] <= data_in[15:8];         // Upper 8 bits of data_in
                fifo[wr_ptr + 1] <= data_in[7:0];      // Lower 8 bits of data_in
                wr_ptr <= (wr_ptr + 2) % FIFO_DEPTH;   // Increment write pointer by 2, wrap if necessary
                count <= count + 2;                    // Increment count by 2
            end
            
            // Read operation (Combine two 8-bit FIFO entries into one 16-bit data_out)
            if (rd_en && (count >= 2)) begin
                data_out <= {fifo[rd_ptr], fifo[rd_ptr + 1]}; // Concatenate two 8-bit values to 16-bit
                rd_ptr <= (rd_ptr + 2) % FIFO_DEPTH;          // Increment read pointer by 2, wrap if necessary
                count <= count - 2;                           // Decrement count by 2
            end
            
            // Update full and empty flags
            full <= (count >= FIFO_DEPTH - 1);
            empty <= (count == 0);
        end
    end
endmodule

tb_fifo.v
`timescale 1ns / 1ps

module tb_fifo;
    reg clk;
    reg rst_n;
    reg wr_en;
    reg rd_en;
    reg [15:0] data_in;
    wire [15:0] data_out;
    wire full;
    wire empty;

    // Instantiate the FIFO module
    fifo uut (
        .clk(clk),
        .rst_n(rst_n),
        .wr_en(wr_en),
        .rd_en(rd_en),
        .data_in(data_in),
        .data_out(data_out),
        .full(full),
        .empty(empty)
    );
    initial begin
        $dumpfile("fifo_testbench.vcd"); // Specifies the VCD output file name
        $dumpvars(0, tb_fifo);           // Dumps all variables in the tb_fifo module
    end

    // Clock generation
    always begin
        clk = 0; #5;
        clk = 1; #5;
    end

    // Test sequence
    initial begin
        // Initialize signals
        rst_n = 0;
        wr_en = 0;
        rd_en = 0;
        data_in = 0;

        // Apply reset
        #10;
        rst_n = 1; // Release reset

        // Test case 1: Write first data to FIFO
        wr_en = 1; // Enable write
        data_in = 16'hABCD; // First data
        #10; // Wait for a clock cycle

        // Test case 1: Write second data to FIFO
        data_in = 16'h1234; // Second data
        #10; // Wait for a clock cycle

        // Disable write and check full flag
        wr_en = 0; 
        #10; 

        if (full) begin
            $display("FIFO is full at time %0t after writing two items.", $time);
        end else begin
            $display("FIFO is not full at time %0t after writing two items.", $time);
        end

        // Test case 2: Read data from FIFO
        rd_en = 1; // Enable read
        #10; // Wait for a clock cycle

        // Check output data
        if (!empty) begin
            $display("Read data: %h at time %0t", data_out, $time);
        end else begin
            $display("FIFO is empty at time %0t", $time);
        end

        // Read next data
        #10; // Wait for a clock cycle
        if (!empty) begin
            $display("Read data: %h at time %0t", data_out, $time);
        end else begin
            $display("FIFO is empty at time %0t", $time);
        end

        // Disable read after reading
        rd_en = 0; 
        #10;

        // Test case 3: Write additional data to FIFO
        wr_en = 1; // Enable write
        data_in = 16'h5678; // Third data
        #10; // Wait for a clock cycle

        // Write fourth data to FIFO
        data_in = 16'h9ABC; // Fourth data
        #10; // Wait for a clock cycle

        // Disable write
        wr_en = 0; 
        #10;

        // Check if FIFO is full after writing two more items
        if (full) begin
            $display("FIFO is full at time %0t after writing additional items.", $time);
        end else begin
            $display("FIFO is not full at time %0t after writing additional items.", $time);
        end

        // Test case 4: Read all remaining data from FIFO
        rd_en = 1; // Enable read
        #10; // Wait for a clock cycle

        // Check output data
        if (!empty) begin
            $display("Read data: %h at time %0t", data_out, $time);
        end else begin
            $display("FIFO is empty at time %0t", $time);
        end

        // Read next data
        #10; // Wait for a clock cycle
        if (!empty) begin
            $display("Read data: %h at time %0t", data_out, $time);
        end else begin
            $display("FIFO is empty at time %0t", $time);
        end

        // Final read
        #10; // Wait for a clock cycle
        if (!empty) begin
            $display("Read data: %h at time %0t", data_out, $time);
        end else begin
            $display("FIFO is empty at time %0t", $time);
        end

        // Disable read after reading
        rd_en = 0; 
        #10;

        // Finish simulation
        $finish;
    end

    // Monitor outputs
    initial begin
        $monitor("Time: %0t | wr_en: %b | rd_en: %b | data_in: %h | data_out: %h | full: %b | empty: %b", 
                 $time, wr_en, rd_en, data_in, data_out, full, empty);
    end
endmodule

fifo_testbench.vcd
$date
	Fri Nov  1 20:48:13 2024
$end
$version
	Icarus Verilog
$end
$timescale
	1ps
$end
$scope module tb_fifo $end
$var wire 1 ! full $end
$var wire 1 " empty $end
$var wire 16 # data_out [15:0] $end
$var reg 1 $ clk $end
$var reg 16 % data_in [15:0] $end
$var reg 1 & rd_en $end
$var reg 1 ' rst_n $end
$var reg 1 ( wr_en $end
$scope module uut $end
$var wire 1 $ clk $end
$var wire 16 ) data_in [15:0] $end
$var wire 1 & rd_en $end
$var wire 1 ' rst_n $end
$var wire 1 ( wr_en $end
$var reg 6 * count [5:0] $end
$var reg 16 + data_out [15:0] $end
$var reg 1 " empty $end
$var reg 1 ! full $end
$var reg 5 , rd_ptr [4:0] $end
$var reg 5 - wr_ptr [4:0] $end
$upscope $end
$upscope $end
$enddefinitions $end
#0
$dumpvars
b0 -
b0 ,
b0 +
b0 *
b0 )
0(
0'
0&
b0 %
0$
b0 #
1"
0!
$end
#5000
1$
#10000
0$
b1010101111001101 %
b1010101111001101 )
1(
1'
#15000
b10 *
b10 -
1$
#20000
0$
b1001000110100 %
b1001000110100 )
#25000
0"
b100 *
b100 -
1$
#30000
0$
0(
#35000
1$
#40000
0$
1&
#45000
b10 *
b10 ,
b1010101111001101 #
b1010101111001101 +
1$
#50000
0$
#55000
b0 *
b100 ,
b1001000110100 #
b1001000110100 +
1$
#60000
0$
0&
#65000
1"
1$
#70000
0$
b101011001111000 %
b101011001111000 )
1(
#75000
b10 *
b110 -
1$
#80000
0$
b1001101010111100 %
b1001101010111100 )
#85000
0"
b100 *
b1000 -
1$
#90000
0$
0(
#95000
1$
#100000
0$
1&
#105000
b10 *
b110 ,
b101011001111000 #
b101011001111000 +
1$
#110000
0$
#115000
b0 *
b1000 ,
b1001101010111100 #
b1001101010111100 +
1$
#120000
0$
#125000
1"
1$
#130000
0$
0&
